aristopy/__init__.py
aristopy/bus.py
aristopy/component.py
aristopy/conversion.py
aristopy/energySystem.py
aristopy/flowSeriesVar.py
aristopy/logger.py
aristopy/plotter.py
aristopy/solar.py
aristopy/sourceSink.py
aristopy/storage.py
aristopy/utils.py
aristopy-0.9.4.dist-info/LICENSE.txt
aristopy-0.9.4.dist-info/METADATA
aristopy-0.9.4.dist-info/WHEEL
aristopy-0.9.4.dist-info/top_level.txt
aristopy-0.9.4.dist-info/RECORD
