Metadata-Version: 2.1
Name: aristopy
Version: 0.9.4
Summary: Framework for the optimization of energy systems
Home-page: https://git.tu-berlin.de/etus/public/aristopy.git
Author: Stefan Bruche
Author-email: aristopy@gmail.com
License: MIT license
Project-URL: Documentation, https://aristopy.readthedocs.io/en/latest/index.html
Keywords: energy systems,optimization,pyomo
Platform: UNKNOWN
Classifier: Development Status :: 3 - Alpha
Classifier: Intended Audience :: Science/Research
Classifier: Intended Audience :: End Users/Desktop
Classifier: License :: OSI Approved :: MIT License
Classifier: Natural Language :: English
Classifier: Operating System :: OS Independent
Classifier: Programming Language :: Python :: 3
Classifier: Programming Language :: Python :: 3.6
Classifier: Programming Language :: Python :: 3.7
Classifier: Topic :: Scientific/Engineering :: Mathematics
Classifier: Topic :: Software Development :: Libraries :: Python Modules
License-File: LICENSE.txt
Requires-Dist: pandas (>=0.19.2)
Requires-Dist: numpy (>=1.11.3)
Requires-Dist: pyomo (>=5.6.9)
Requires-Dist: tsam (>=1.1.0)
Requires-Dist: xlrd (>=1.0.0)
Requires-Dist: openpyxl
Requires-Dist: matplotlib
Provides-Extra: dev
Requires-Dist: pytest ; extra == 'dev'
Requires-Dist: sphinx ; extra == 'dev'
Requires-Dist: sphinx-rtd-theme (>=0.4.3) ; extra == 'dev'
Requires-Dist: nbsphinx ; extra == 'dev'
Requires-Dist: ipython ; extra == 'dev'
Requires-Dist: twine ; extra == 'dev'
